{
  "acm.title": "Aggiungi un'azienda",
  "acm.subtitle": "Crea un nuovo workspace cliente da gestire",
  "acm.placeholder": "Es. Acme S.r.l.",
  "acm.helper": "Dopo la creazione entrerai nel nuovo workspace, dove potrai collegare le sue integrazioni (Meta, Klaviyo, Shopify, Google).",
  "acm.creating": "Creazione…",
  "acm.createWorkspace": "Crea workspace",
  "settings.comingSoon": "Disponibile a breve",
  "settings.founderOffer": "Founder: −30% A VITA per le prime 100 aziende",
  "sched.weeklyTime": "Ogni lunedì alle 09:00 UTC",
  "sched.monthlyTime": "Primo del mese alle 09:00 UTC"
}